callviz/__init__.py
callviz/core.py
callviz/node.py
callviz/tree.py
callviz/utility.py
callviz-0.2.0.dist-info/LICENSE
callviz-0.2.0.dist-info/METADATA
callviz-0.2.0.dist-info/WHEEL
callviz-0.2.0.dist-info/top_level.txt
callviz-0.2.0.dist-info/RECORD
