Metadata-Version: 2.1
Name: callviz
Version: 0.2.0
Summary: Recursive function calls visualization using Graphviz
Home-page: https://github.com/theobori/callviz
Author: Théo Bori
Author-email: nagi@tilde.team
License: MIT License
License-File: LICENSE
Requires-Dist: graphviz
